README.md
setup.py
neuro_summary.egg-info/PKG-INFO
neuro_summary.egg-info/SOURCES.txt
neuro_summary.egg-info/dependency_links.txt
neuro_summary.egg-info/entry_points.txt
neuro_summary.egg-info/requires.txt
neuro_summary.egg-info/top_level.txt
src/__init__.py
src/config.py
src/summary_statistics.py
src/p_util/__init__.py
src/p_util/old_util.py
src/p_util/plots.py
src/p_util/preprocessing.py
src/p_util/spike_detection.py