Metadata-Version: 1.2
Name: neuro-summary
Version: 0.0.0.2
Summary: Runs a statistical summary for electrophysiology data.
Home-page: https://github.com/
Author-email: lehenry@ucsd.edu
License: UNKNOWN
Platform: UNKNOWN
Classifier: Programming Language :: Python :: 3
Classifier: License :: OSI Approved :: MIT License
Classifier: Operating System :: OS Independent
Requires-Python: >=3.7
